volkoff/__init__.py
volkoff/extract.py
volkoff/hide.py
volkoff/main.py
volkoff/py.typed
volkoff/tests.py
volkoff/tui.py
volkoff/utils.py
volkoff-0.1.45.dist-info/METADATA
volkoff-0.1.45.dist-info/WHEEL
volkoff-0.1.45.dist-info/entry_points.txt
volkoff-0.1.45.dist-info/RECORD
