Metadata-Version: 2.3
Name: volkoff
Version: 0.1.45
Summary: Simple terminal based file encryption tool using AES-256-GCM
Requires-Python: >=3.12
Requires-Dist: base58>=2.1.1
Requires-Dist: cryptography>=43.0.3
Requires-Dist: ecdsa>=0.19.0
Requires-Dist: keyboard>=0.13.5
Requires-Dist: pytest>=8.3.3
Requires-Dist: questionary>=1.10.0
Requires-Dist: rich>=13.9.4
